datajoint_link-0.11.dist-info/METADATA
datajoint_link-0.11.dist-info/WHEEL
datajoint_link-0.11.dist-info/licenses/LICENSE.txt
link/__init__.py
link/adapters/__init__.py
link/adapters/controller.py
link/adapters/custom_types.py
link/adapters/facade.py
link/adapters/gateway.py
link/adapters/identification.py
link/adapters/present.py
link/adapters/progress.py
link/domain/__init__.py
link/domain/commands.py
link/domain/custom_types.py
link/domain/events.py
link/domain/link.py
link/domain/state.py
link/infrastructure/__init__.py
link/infrastructure/config.py
link/infrastructure/dj_helpers.py
link/infrastructure/facade.py
link/infrastructure/factory.py
link/infrastructure/link.py
link/infrastructure/mixin.py
link/infrastructure/progress.py
link/infrastructure/sequence.py
link/service/__init__.py
link/service/gateway.py
link/service/handlers.py
link/service/messagebus.py
link/service/progress.py
link/service/uow.py
datajoint_link-0.11.dist-info/RECORD
