Metadata-Version: 2.1
Name: datajoint-link
Version: 0.11
Summary: A tool for linking two DataJoint tables located on different database servers
Home-page: https://github.com/sinzlab/link
Author-Email: Christoph Blessing <33834216+cblessing24@users.noreply.github.com>
License: GNU GPLv3
Classifier: Programming Language :: Python :: 3
Classifier: License :: OSI Approved :: GNU General Public License v3 (GPLv3)
Classifier: Operating System :: OS Independent
Classifier: Topic :: Database
Project-URL: Homepage, https://github.com/sinzlab/link
Requires-Python: >=3.8
Requires-Dist: datajoint>=0.12
Requires-Dist: tqdm>=4.66.1
